live_chrono/__init__.py
live_chrono/live_chrono.py
live_chrono/model.py
live_chrono/utils.py
live_chrono-1.0.0.dist-info/licenses/LICENSE
live_chrono-1.0.0.dist-info/METADATA
live_chrono-1.0.0.dist-info/WHEEL
live_chrono-1.0.0.dist-info/top_level.txt
live_chrono-1.0.0.dist-info/RECORD
