Metadata-Version: 2.4
Name: live-chrono
Version: 1.0.0
Summary: Live-updating elapsed timer
Home-page: https://github.com/TuronLab/LiveChrono
Author: Pablo Turon
Author-email: ptmallor@gmail.com
License: MIT
Keywords: timer live elapsed progress chrono
Classifier: Programming Language :: Python :: 3
Classifier: License :: OSI Approved :: MIT License
Classifier: Operating System :: OS Independent
Classifier: Development Status :: 4 - Beta
Classifier: Intended Audience :: Developers
Classifier: Topic :: Utilities
Requires-Python: >=3.7
License-File: LICENSE
Dynamic: author
Dynamic: author-email
Dynamic: classifier
Dynamic: description
Dynamic: description-content-type
Dynamic: home-page
Dynamic: keywords
Dynamic: license
Dynamic: license-file
Dynamic: requires-python
Dynamic: summary
